README
setup.py
parallel_run/__init__.py
parallel_run/base_manager.py
parallel_run/base_motor.py
parallel_run/tools.py
parallel_run.egg-info/PKG-INFO
parallel_run.egg-info/SOURCES.txt
parallel_run.egg-info/dependency_links.txt
parallel_run.egg-info/requires.txt
parallel_run.egg-info/top_level.txt