Metadata-Version: 1.0
Name: parallel-run
Version: 1.2.9
Summary: a parallel package mainly using multiprocessing
Home-page: http://weibo.com/zhoujingjiang/
Author: zhoujingjiang
Author-email: jingjiang@staff.sina.com.cn
License: LGPL
Platform: UNKNOWN
